{
  "parent": "minecraft:recipes/root",
  "rewards": {
    "recipes": [
      "thermal:lumium_ingot_4_no_smelter"
    ]
  },
  "criteria": {
    "has_glowstone_dust": {
      "trigger": "minecraft:inventory_changed",
      "conditions": {
        "items": [
          {
            "tag": "forge:dusts/glowstone"
          }
        ]
      }
    },
    "has_the_recipe": {
      "trigger": "minecraft:recipe_unlocked",
      "conditions": {
        "recipe": "thermal:lumium_ingot_4_no_smelter"
      }
    }
  },
  "requirements": [
    [
      "has_glowstone_dust",
      "has_the_recipe"
    ]
  ]
}